xSide_Languages/__init__.py
xSide_Languages/plugin.cpython-311-darwin.so
xSide_Languages/plugin.pyi
xside_languages-2026.1.5a0.dist-info/METADATA
xside_languages-2026.1.5a0.dist-info/WHEEL
xside_languages-2026.1.5a0.dist-info/entry_points.txt
xside_languages-2026.1.5a0.dist-info/top_level.txt
xside_languages-2026.1.5a0.dist-info/RECORD
