Metadata-Version: 2.4
Name: xSide-Languages
Version: 2026.1.5a0
Summary: X Qt framework.
Home-page: 
Author: Connet Information Technology Company Ltd, Shanghai.
Author-email: tech_support@shconnet.com.cn
Keywords: Qt Python
Classifier: Intended Audience :: Developers
Classifier: Programming Language :: Python
Classifier: Programming Language :: Python :: 3.6
Classifier: Programming Language :: Python :: 3.7
Classifier: Programming Language :: Python :: 3.8
Classifier: Programming Language :: Python :: 3.9
Classifier: Programming Language :: Python :: 3.10
Classifier: Programming Language :: Python :: 3.11
Classifier: Programming Language :: Python :: Implementation :: CPython
Classifier: Topic :: Software Development :: Interpreters
Requires-Dist: xSide
Dynamic: author
Dynamic: author-email
Dynamic: classifier
Dynamic: description-content-type
Dynamic: keywords
Dynamic: requires-dist
Dynamic: summary
